{"q95n6RoLVZ7AmA16wRwAAA==":"bg3-600x600.jpg","hSErjHxSvh/lCJlv3kbbaw==":"bg6-1187x791.jpg","1vUmsalxekRacxxPsjK9hg==":"bg7-1920x1280.jpg","QMEWNUfozZnBkZk/tOiAkw==":"cval-626x469.jpg","KyKUlqKK40H98E7ldN5qUA==":"quarrying-626x351.jpg","+kkN1ZRXGIOLb3iN+3no3g==":"stone-602x802.jpg","bEb0tfVAfF3k+1IzTPL7rQ==":"safe-626x447.jpg","ASNk2R4eTmCF9StGRuWSZQ==":"dnaco-278x90.png","2CKoED6/oeo77VPWULA47Q==":"ambitious-400x131.png","pOn9eg1uw/v3aScP+L+0cw==":"jaf-2-400x400.png","wNCcBy/0lexyuvEUvnKs8g==":"logoc-137x137.jpg","4+05Ir4B3fQV86Io6GWlPQ==":"bg2-1187x791.png","GfWiHE7HSnclz4a/y6y/AA==":"picture3-561x253.jpg","R/bVWlOagOObHkLSDcwW0w==":"picture4-561x253.jpg","ggfVMl8fIMMlcx1GulzBtA==":"picture7-561x253.jpg","E/2Av/t3wod5Lsvqio+X0A==":"picture8-561x253.jpg","XqStexa3ucYeWEdbgE9USg==":"background1.jpg","IsZWM88qGUjChr2meyJOQQ==":"hel-626x500.jpg"}